winidjango/__init__.py
winidjango/dev/__init__.py
winidjango/dev/builders/__init__.py
winidjango/dev/cli/__init__.py
winidjango/dev/cli/shared_subcommands.py
winidjango/dev/cli/subcommands.py
winidjango/dev/configs/__init__.py
winidjango/dev/configs/configs.py
winidjango/dev/management/__init__.py
winidjango/dev/tests/__init__.py
winidjango/dev/tests/fixtures/__init__.py
winidjango/main.py
winidjango/py.typed
winidjango/resources/__init__.py
winidjango/src/__init__.py
winidjango/src/commands/__init__.py
winidjango/src/commands/base/__init__.py
winidjango/src/commands/base/base.py
winidjango/src/commands/import_data.py
winidjango/src/db/__init__.py
winidjango/src/db/bulk.py
winidjango/src/db/fields.py
winidjango/src/db/models.py
winidjango/src/db/sql.py
winidjango-2.0.66.dist-info/licenses/LICENSE
winidjango-2.0.66.dist-info/WHEEL
winidjango-2.0.66.dist-info/entry_points.txt
winidjango-2.0.66.dist-info/METADATA
winidjango-2.0.66.dist-info/RECORD
