Metadata-Version: 2.4
Name: winidjango
Version: 2.0.66
Summary: A utils package for django
Keywords: 
Author: Winipedia
License-Expression: MIT
License-File: LICENSE
Classifier: Programming Language :: Python :: 3.12
Classifier: Programming Language :: Python :: 3.13
Classifier: Programming Language :: Python :: 3.14
Classifier: Operating System :: OS Independent
Classifier: Typing :: Typed
Requires-Dist: django
Requires-Dist: django-stubs-ext
Requires-Dist: winiutils
Maintainer: Winipedia
Requires-Python: >=3.12
Project-URL: Changelog, https://github.com/Winipedia/winidjango/releases
Project-URL: Documentation, https://Winipedia.github.io/winidjango
Project-URL: Homepage, https://github.com/Winipedia/winidjango
Project-URL: Issues, https://github.com/Winipedia/winidjango/issues
Project-URL: Source, https://github.com/Winipedia/winidjango
